eventuality/__init__.py
eventuality-1.0.0.dist-info/LICENSE.md
eventuality-1.0.0.dist-info/METADATA
eventuality-1.0.0.dist-info/WHEEL
eventuality-1.0.0.dist-info/top_level.txt
eventuality-1.0.0.dist-info/RECORD
