Metadata-Version: 2.1
Name: eventuality
Version: 1.0.0
Summary: An intuitive and Pythonic event library.
Home-page: https://github.com/Avlyssna/eventuality
Author: Avlyssna
Author-email: avlyssna@gmail.com
License: MIT
Keywords: Events Event Callbacks Callback
Platform: UNKNOWN
